pytput/__init__.py
pytput/__main__.py
pytput/formatter.py
pytput/style.py
pytput/tput.py
pytput/utils.py
pytput-0.4.0.dist-info/LICENSE
pytput-0.4.0.dist-info/METADATA
pytput-0.4.0.dist-info/WHEEL
pytput-0.4.0.dist-info/entry_points.txt
pytput-0.4.0.dist-info/top_level.txt
pytput-0.4.0.dist-info/RECORD
