Metadata-Version: 2.1
Name: pytput
Version: 0.4.0
Summary: Python3 API to format messages using colors and styles
Home-page: https://github.com/essembeh/pytput
Author: Sébastien MB
Author-email: seb@essembeh.org
License: Mozilla Public License Version 2.0
Platform: UNKNOWN
Classifier: Development Status :: 4 - Beta
Classifier: Environment :: Console
Classifier: Intended Audience :: Developers
Classifier: License :: OSI Approved :: Mozilla Public License 2.0 (MPL 2.0)
Classifier: Topic :: Utilities
Classifier: License :: OSI Approved :: Apache Software License
Classifier: Programming Language :: Python :: 3.6
Classifier: Programming Language :: Python :: 3.7
Classifier: Programming Language :: Python :: 3.8
Classifier: Programming Language :: Python :: 3 :: Only
Classifier: Topic :: Software Development :: Libraries
Classifier: Topic :: Terminals :: Terminal Emulators/X Terminals
Classifier: Topic :: Utilities
Requires-Python: >=3.6.0
Requires-Dist: dataclasses ; python_version < "3.7"
